{
  "enderlink_msg1": {
    "subtitle": "subtitles.enderlink_msg1",
    "sounds": [
      {
        "name": "royalrealms:metaprise_applications_-_angelbottm_mod_pack_v1.081417_-_02_angelbot-msg01",
        "stream": false
      }
    ]
  },
  "enderlink_msg2": {
    "subtitle": "subtitles.enderlink_msg2",
    "sounds": [
      {
        "name": "royalrealms:metaprise_applications_-_angelbottm_mod_pack_v1.081417_-_04_angelbot-msg02",
        "stream": false
      }
    ]
  },
  "enderlink_msg3": {
    "subtitle": "subtitles.enderlink_msg3",
    "sounds": [
      {
        "name": "royalrealms:metaprise_applications_-_angelbottm_mod_pack_v1.081417_-_06_angelbot-msg03",
        "stream": false
      }
    ]
  },
  "enderlink_msg_rare": {
    "subtitle": "subtitles.enderlink_msg_rare",
    "sounds": [
      {
        "name": "royalrealms:metaprise_applications_-_angelbottm_mod_pack_v1.081417_-_08_angelbot-msg_dlt01",
        "stream": false
      }
    ]
  },
  "enderlink_boot": {
    "subtitle": "subtitles.enderlink_boot",
    "sounds": [
      {
        "name": "royalrealms:metaprise_applications_-_angelbottm_mod_pack_v1.081417_-_09_xlife",
        "stream": false
      }
    ]
  },
  "enderlink_boot_rare1": {
    "subtitle": "subtitles.enderlink_boot_rare1",
    "sounds": [
      {
        "name": "royalrealms:metaprise_applications_-_angelbottm_mod_pack_v1.081417_-_24_ylife",
        "stream": false
      }
    ]
  },
  "enderlink_boot_rare2": {
    "subtitle": "subtitles.enderlink_boot_rare2",
    "sounds": [
      {
        "name": "royalrealms:metaprise_applications_-_angelbottm_mod_pack_v1.081417_-_39_zlife",
        "stream": false
      }
    ]
  },
  "enderlink_boot_rare3": {
    "subtitle": "subtitles.enderlink_boot_rare3",
    "sounds": [
      {
        "name": "royalrealms:metaprise_applications_-_angelbottm_mod_pack_v1.081417_-_54_alife",
        "stream": false
      }
    ]
  },
  "thunderstrike_warning": {
    "sounds": [
      {
        "name": "royalrealms:thunder",
        "stream": false
      }
    ]
  },
  "record_sunlight_blocked": {
    "sounds": [
      {
        "name": "royalrealms:record_sunlight_blocked",
        "stream": true
      }
    ]
  },
  "record_7l011": {
    "sounds": [
      {
        "name": "royalrealms:record_7l011",
        "stream": true
      }
    ]
  },
  "record_dissolving_dark_clouds": {
    "sounds": [
      {
        "name": "royalrealms:record_dissolving_dark_clouds",
        "stream": true
      }
    ]
  },
  "crystal_break": {
    "sounds": [
      {
        "name": "royalrealms:crystal_break1",
        "stream": false
      },
      {
        "name": "royalrealms:crystal_break2",
        "stream": false
      }
    ]
  },
  "record_black_knife": {
    "sounds": [
      {
        "name": "royalrealms:record_black_knife",
        "stream": true
      }
    ]
  },
  "record_tv_time": {
    "sounds": [
      {
        "name": "royalrealms:record_tv_time",
        "stream": true
      }
    ]
  },
  "record_glowing_snow": {
    "sounds": [
      {
        "name": "royalrealms:record_glowing_snow",
        "stream": true
      }
    ]
  },
  "record_uwah_so_temperate": {
    "sounds": [
      {
        "name": "royalrealms:record_uwah_so_temperate",
        "stream": true
      }
    ]
  },
  "record_tv_world": {
    "sounds": [
      {
        "name": "royalrealms:record_tv_world",
        "stream": true
      }
    ]
  },
  "record_core": {
    "sounds": [
      {
        "name": "royalrealms:record_core",
        "stream": true
      }
    ]
  },
  "swoon": {
    "sounds": [
      {
        "name": "royalrealms:black_knife_swoon",
        "stream": false
      }
    ]
  },
  "record_healing": {
    "sounds": [
      {
        "name": "royalrealms:record_healing1",
        "stream": true
      },
      {
        "name": "royalrealms:record_healing2",
        "stream": true
      },
      {
        "name": "royalrealms:record_healing3",
        "stream": true
      },
      {
        "name": "royalrealms:record_healing4",
        "stream": true
      },
      {
        "name": "royalrealms:record_healing5",
        "stream": true
      },
      {
        "name": "royalrealms:record_healing6",
        "stream": true
      },
      {
        "name": "royalrealms:record_healing7",
        "stream": true
      }
    ]
  },
  "record_born": {
    "sounds": [
      {
        "name": "royalrealms:record_born1",
        "stream": true
      },
      {
        "name": "royalrealms:record_born2",
        "stream": true
      },
      {
        "name": "royalrealms:record_born3",
        "stream": true
      },
      {
        "name": "royalrealms:record_born4",
        "stream": true
      },
      {
        "name": "royalrealms:record_born5",
        "stream": true
      },
      {
        "name": "royalrealms:record_born6",
        "stream": true
      },
      {
        "name": "royalrealms:record_born7",
        "stream": true
      },
      {
        "name": "royalrealms:record_born8",
        "stream": true
      },
      {
        "name": "royalrealms:record_born9",
        "stream": true
      },
      {
        "name": "royalrealms:record_born10",
        "stream": true
      }
    ]
  },
  "record_bumblebee": {
    "sounds": [
      {
        "name": "royalrealms:record_bumblebee",
        "stream": true
      }
    ]
  },
  "record_moth": {
    "sounds": [
      {
        "name": "royalrealms:record_moth",
        "stream": true
      }
    ]
  },
  "record_isopod": {
    "sounds": [
      {
        "name": "royalrealms:record_isopod",
        "stream": true
      }
    ]
  },
  "record_scarab": {
    "sounds": [
      {
        "name": "royalrealms:record_scarab",
        "stream": true
      }
    ]
  },
  "record_spiny_spider": {
    "sounds": [
      {
        "name": "royalrealms:record_spiny_spider",
        "stream": true
      }
    ]
  },
  "record_weevil": {
    "sounds": [
      {
        "name": "royalrealms:record_weevil",
        "stream": true
      }
    ]
  },
  "record_butterfly": {
    "sounds": [
      {
        "name": "royalrealms:record_butterfly",
        "stream": true
      }
    ]
  },
  "record_treehopper": {
    "sounds": [
      {
        "name": "royalrealms:record_treehopper",
        "stream": true
      }
    ]
  },
  "record_tortoise_beetle": {
    "sounds": [
      {
        "name": "royalrealms:record_tortoise_beetle",
        "stream": true
      }
    ]
  }
}