{
  "_fv": 66,
  "_type": "blockstates",
  "definition": {
    "block": "SpectralBlock",
    "blockstateList": [
      {
        "texture": "spectral_block_1",
        "textureTop": "",
        "textureLeft": "",
        "textureFront": "",
        "textureRight": "",
        "textureBack": "",
        "particleTexture": "",
        "renderType": 4,
        "customModelName": "Single texture",
        "luminance": 0,
        "boundingBoxes": []
      },
      {
        "texture": "spectral_block_2",
        "textureTop": "",
        "textureLeft": "",
        "textureFront": "",
        "textureRight": "",
        "textureBack": "",
        "particleTexture": "",
        "renderType": 4,
        "customModelName": "Single texture",
        "luminance": 0,
        "boundingBoxes": []
      },
      {
        "texture": "spectral_block_3",
        "textureTop": "",
        "textureLeft": "",
        "textureFront": "",
        "textureRight": "",
        "textureBack": "",
        "particleTexture": "",
        "renderType": 4,
        "customModelName": "Single texture",
        "luminance": 0,
        "boundingBoxes": []
      },
      {
        "texture": "spectral_block_4",
        "textureTop": "",
        "textureLeft": "",
        "textureFront": "",
        "textureRight": "",
        "textureBack": "",
        "particleTexture": "",
        "renderType": 4,
        "customModelName": "Single texture",
        "luminance": 0,
        "boundingBoxes": []
      },
      {
        "texture": "spectral_block_5",
        "textureTop": "",
        "textureLeft": "",
        "textureFront": "",
        "textureRight": "",
        "textureBack": "",
        "particleTexture": "",
        "renderType": 4,
        "customModelName": "Single texture",
        "luminance": 0,
        "boundingBoxes": []
      }
    ]
  }
}